PySAM/Battery.cpython-310-darwin.so
PySAM/Battery.pyi
PySAM/BatteryStateful.cpython-310-darwin.so
PySAM/BatteryStateful.pyi
PySAM/BatteryTools.py
PySAM/Battwatts.cpython-310-darwin.so
PySAM/Battwatts.pyi
PySAM/Belpe.cpython-310-darwin.so
PySAM/Belpe.pyi
PySAM/Biomass.cpython-310-darwin.so
PySAM/Biomass.pyi
PySAM/Cashloan.cpython-310-darwin.so
PySAM/Cashloan.pyi
PySAM/CashloanHeat.cpython-310-darwin.so
PySAM/CashloanHeat.pyi
PySAM/CbConstructionFinancing.cpython-310-darwin.so
PySAM/CbConstructionFinancing.pyi
PySAM/CbEmpiricalHceHeatLoss.cpython-310-darwin.so
PySAM/CbEmpiricalHceHeatLoss.pyi
PySAM/Communitysolar.cpython-310-darwin.so
PySAM/Communitysolar.pyi
PySAM/CspDsgLfUi.cpython-310-darwin.so
PySAM/CspDsgLfUi.pyi
PySAM/CspHeatsink.cpython-310-darwin.so
PySAM/CspHeatsink.pyi
PySAM/CspSubcomponent.cpython-310-darwin.so
PySAM/CspSubcomponent.pyi
PySAM/CustomGeneration.cpython-310-darwin.so
PySAM/CustomGeneration.pyi
PySAM/Equpartflip.cpython-310-darwin.so
PySAM/Equpartflip.pyi
PySAM/EtesElectricResistance.cpython-310-darwin.so
PySAM/EtesElectricResistance.pyi
PySAM/EtesPtes.cpython-310-darwin.so
PySAM/EtesPtes.pyi
PySAM/FresnelPhysical.cpython-310-darwin.so
PySAM/FresnelPhysical.pyi
PySAM/FresnelPhysicalIph.cpython-310-darwin.so
PySAM/FresnelPhysicalIph.pyi
PySAM/Fuelcell.cpython-310-darwin.so
PySAM/Fuelcell.pyi
PySAM/Geothermal.cpython-310-darwin.so
PySAM/Geothermal.pyi
PySAM/GeothermalCosts.cpython-310-darwin.so
PySAM/GeothermalCosts.pyi
PySAM/Grid.cpython-310-darwin.so
PySAM/Grid.pyi
PySAM/Hcpv.cpython-310-darwin.so
PySAM/Hcpv.pyi
PySAM/HostDeveloper.cpython-310-darwin.so
PySAM/HostDeveloper.pyi
PySAM/Hybrid.cpython-310-darwin.so
PySAM/Hybrid.pyi
PySAM/HybridSteps.cpython-310-darwin.so
PySAM/HybridSteps.pyi
PySAM/Iec61853interp.cpython-310-darwin.so
PySAM/Iec61853interp.pyi
PySAM/Iec61853par.cpython-310-darwin.so
PySAM/Iec61853par.pyi
PySAM/InvCecCg.cpython-310-darwin.so
PySAM/InvCecCg.pyi
PySAM/IphToLcoefcr.cpython-310-darwin.so
PySAM/IphToLcoefcr.pyi
NREL_PySAM-7.1.0.dist-info/LICENSE
NREL_PySAM-7.1.0.dist-info/METADATA
NREL_PySAM-7.1.0.dist-info/WHEEL
NREL_PySAM-7.1.0.dist-info/top_level.txt
NREL_PySAM-7.1.0.dist-info/RECORD
