Metadata-Version: 2.1
Name: NREL-PySAM
Version: 7.1.0
Summary: National Renewable Energy Laboratory's System Advisor Model Python Wrapper
Home-page: https://nrel-pysam.readthedocs.io
Author: dguittet
Author-email: dguittet@nrel.gov
License: BSD 3-Clause
License-File: LICENSE
